{
    "apps": [
        {
            "name"        : "treasureService",
            "script"      : "./snatch_treasure.js",
            "watch"       : false,
            "cwd"         : "./",
            "error_file"  : "../logs/treasureService-err.log",
            "out_file"    : "../logs/treasureService-out.log"
        },
        {
            "name"        : "treasureListenTransfer",
            "script"      : "./listenTransfer.js",
            "watch"       : false,
            "cwd"         : "./src/job",
            "error_file"  : "../../../logs/treasureListenTransfer-err.log",
            "out_file"    : "../../../logs/treasureListenTransfer-out.log"
        },
        {
            "name"        : "treasureMqHandler",
            "script"      : "./mqHandler.js",
            "watch"       : false,
            "cwd"         : "./src/job",
            "error_file"  : "../../../logs/treasureMqHandler-err.log",
            "out_file"    : "../../../logs/treasureMqHandler-out.log"
        }
    ]
}